CHANGELOG.md
LICENSE
MANIFEST.in
README.rst
requirements.txt
setup.cfg
setup.py
property_caching/__init__.py
property_caching.egg-info/PKG-INFO
property_caching.egg-info/SOURCES.txt
property_caching.egg-info/dependency_links.txt
property_caching.egg-info/top_level.txt
tests/__init__.py
tests/test_property_caching.py