Metadata-Version: 1.1
Name: property-caching
Version: 1.0.3
Summary: Property caching
Home-page: https://github.com/yola/property-caching
Author: Yola
Author-email: engineers@yola.com
License: MIT (Expat)
Platform: UNKNOWN
Classifier: Programming Language :: Python :: 2
Classifier: Programming Language :: Python :: 3
Classifier: Development Status :: 5 - Production/Stable
Classifier: License :: OSI Approved :: MIT License
